<Dependencies>
  <ProductDependencies>
    <Dependency Name="Microsoft.Dotnet.Sdk.Internal" Version="6.0.300-preview.22175.4">
      <Uri>https://github.com/dotnet/installer</Uri>
      <Sha>6791ff652bd2d5d007b92a66203d3483ca1948cf</Sha>
    </Dependency>
    <Dependency Name="Microsoft.NET.ILLink.Tasks" Version="6.0.200-1.22124.2" CoherentParentDependency="Microsoft.Dotnet.Sdk.Internal">
      <Uri>https://github.com/dotnet/linker</Uri>
      <Sha>e9cfb5413a6a7a7b5bfc3b9a73671be2b18642cf</Sha>
    </Dependency>
    <Dependency Name="Microsoft.NETCore.App.Ref" Version="6.0.4">
      <Uri>https://github.com/dotnet/runtime</Uri>
      <Sha>323bf2dd0ef1004687a8bafa10a0c66f63252dee</Sha>
    </Dependency>
    <!-- This is required for our test apps to build; in some cases Microsoft.AspNetCore.App is pulled in, and when building test apps the build needs to be able to resolve that -->
    <Dependency Name="Microsoft.AspNetCore.App.Ref" Version="6.0.2" CoherentParentDependency="Microsoft.Dotnet.Sdk.Internal">
      <Uri>https://dev.azure.com/dnceng/internal/_git/dotnet-aspnetcore</Uri>
      <Sha>1dcf7acfacf0fe154adcc23270cb0da11ff44ace</Sha>
    </Dependency>
    <Dependency Name="Microsoft.NET.Workload.Emscripten.Manifest-6.0.100" Version="6.0.4" CoherentParentDependency="Microsoft.NETCore.App.Ref">
      <Uri>https://github.com/dotnet/emsdk</Uri>
      <Sha>572aeedcfa16bdb619fafcecf5924e5c6b65b07b</Sha>
    </Dependency>
  </ProductDependencies>
  <ToolsetDependencies>
    <Dependency Name="Microsoft.DotNet.Build.Tasks.Feed" Version="6.0.0-beta.21212.6">
      <Uri>https://github.com/dotnet/arcade</Uri>
      <Sha>db49d790a4bfa977a9ed7436bf2aa242cefae45e</Sha>
    </Dependency>
    <Dependency Name="Microsoft.TemplateEngine.Tasks" Version="7.0.100-alpha.1.21601.1">
      <Uri>https://github.com/dotnet/templating</Uri>
      <Sha />
    </Dependency>
  </ToolsetDependencies>
</Dependencies>
