{
  "author": "Microsoft",
  "name": "Приложение iOS с вкладками",
  "description": "Проект для создания приложения .NET с вкладками для iOS",
  "symbols/bundleId/description": "Переопределяет CFBundleIdentifier в Info.plist",
  "symbols/minOSVersion/description": "Переопределяет SupportedOSPlatformVersion в файле проекта",
  "symbols/deviceFamily/choices/universal/description": "Поддержка устройств iPhone и iPad",
  "symbols/deviceFamily/choices/iphone/description": "Поддерживаются только устройства iPhone",
  "symbols/deviceFamily/choices/ipad/description": "Поддерживаются только устройства iPad"
}